execute.vhd
LIBRARY ieee;
USE ieee.std_logic_1164.ALL;
USE ieee.numeric_std.ALL;

USE work.mydefinitions.ALL;

ENTITY alu IS
	PORT (
		a : IN signed (31 DOWNTO 0);
		b : IN signed (31 DOWNTO 0);
		imm : IN signed (15 DOWNTO 0);
		opC : IN INTEGER RANGE 0 TO 63;
		alu_out : OUT signed (31 DOWNTO 0);
		br_flag : OUT STD_LOGIC
	);
END ENTITY alu;

ARCHITECTURE alu_architecture OF alu IS
	SIGNAL product : signed(63 DOWNTO 0);
BEGIN
	PROCESS (a, b, imm, opC) IS
	BEGIN
		alu_out <= (OTHERS => '-');
		br_flag <= '-';
		CASE opC IS
			WHEN add =>
				alu_out <= a + b;
			WHEN subt =>
				alu_out <= a - b;
			WHEN neg =>
				alu_out <= 0 - a;
			WHEN mul =>
				product <= a * b;
				alu_out <= product(31 DOWNTO 0);
			WHEN div =>
				alu_out <= a / b;
			WHEN modu =>
				alu_out <= a MOD b;
			WHEN nicht =>
				alu_out <= NOT a;
			WHEN und =>
				alu_out <= a AND b;
			WHEN oder =>
				alu_out <= a OR b;
			WHEN beq =>
				IF a = b THEN
					br_flag <= '1';
				ELSE
					br_flag <= '0';
				END IF;
			WHEN bneq =>
				IF a = b THEN
					br_flag <= '0';
				ELSE
					br_flag <= '1';
				END IF;
			WHEN blt =>
				IF a < b THEN
					br_flag <= '1';
				ELSE
					br_flag <= '0';
				END IF;
			WHEN OTHERS =>
				NULL;

		END CASE;

	END PROCESS;

END ARCHITECTURE;

LIBRARY ieee;
USE ieee.std_logic_1164.ALL;
USE ieee.numeric_std.ALL;

USE work.mydefinitions.ALL;

ENTITY execute IS
	PORT (
		clk : IN STD_LOGIC;

		opC : IN INTEGER RANGE 0 TO 63;
		opC_out : OUT INTEGER RANGE 0 TO 63;

		r1 : IN signed (4 DOWNTO 0);
		r2 : IN signed (4 DOWNTO 0);
		imm : IN signed (15 DOWNTO 0);
		r1_out : OUT signed (4 DOWNTO 0);
		r2_out : OUT signed (4 DOWNTO 0);
		imm_out : OUT signed (15 DOWNTO 0);

		long_imm : IN signed (25 DOWNTO 0);
		long_imm_out : OUT signed (25 DOWNTO 0);

		r3 : IN signed (4 DOWNTO 0);
		r4 : IN signed (4 DOWNTO 0);
		r5 : IN signed (4 DOWNTO 0);

		a : IN signed (31 DOWNTO 0);
		b : IN signed (31 DOWNTO 0);

		a_out : OUT signed (31 DOWNTO 0);
		b_out : OUT signed (31 DOWNTO 0);

		pc : IN signed (15 DOWNTO 0);
		pc_out : OUT signed (15 DOWNTO 0);

		br_flag_out : OUT STD_LOGIC


	);
END ENTITY execute;

ARCHITECTURE execute_architecture OF execute IS

	COMPONENT alu IS
		PORT (
			a : IN signed (31 DOWNTO 0);
			b : IN signed (31 DOWNTO 0);
			imm : IN signed (15 DOWNTO 0);
			opC : IN INTEGER RANGE 0 TO 63;
			alu_out : OUT signed (31 DOWNTO 0);
			br_flag : OUT STD_LOGIC
		);
	END COMPONENT alu;

	SIGNAL alu_signal : signed(31 DOWNTO 0);
	SIGNAL br_signal : STD_LOGIC;
BEGIN

	assign : PROCESS (clk) IS
	BEGIN
		IF rising_edge(clk) THEN
			opC_out <= opC;

			r1_out <= r1;
			r2_out <= r2;
			imm_out <= imm;

			long_imm_out <= long_imm;

			a_out <= a;

			pc_out <= pc;

			br_flag_out <= br_signal;
		IF opC = add OR opC = subt OR opC = neg OR opC = mul OR opC = div OR opC = modu OR opC = nicht OR opC = und OR opC = oder THEN
			b_out <= alu_signal;
		ELSE
			b_out <= b;
		end if;

		END IF;
	END PROCESS assign;
	ALUI : alu
	PORT MAP(
		a => a,
		b => b,
		imm => imm,
		opC => opC,
		alu_out => alu_signal,
		br_flag => br_signal
	);

END ARCHITECTURE execute_architecture;

executeTest.vhd
LIBRARY ieee;
USE ieee.std_logic_1164.ALL;
USE ieee.numeric_std.ALL;

ENTITY executeTest IS

END ENTITY executeTest;

ARCHITECTURE testbench OF executeTest IS

    COMPONENT execute IS
        PORT (
            clk : IN STD_LOGIC;

            opC : IN INTEGER RANGE 0 TO 63;
            opC_out : OUT INTEGER RANGE 0 TO 63;

            r1 : IN signed (4 DOWNTO 0);
            r2 : IN signed (4 DOWNTO 0);
            imm : IN signed (15 DOWNTO 0);
            r1_out : OUT signed (4 DOWNTO 0);
            r2_out : OUT signed (4 DOWNTO 0);
            imm_out : OUT signed (15 DOWNTO 0);

            long_imm : IN signed (25 DOWNTO 0);
            long_imm_out : OUT signed (25 DOWNTO 0);

            r3 : IN signed (4 DOWNTO 0);
            r4 : IN signed (4 DOWNTO 0);
            r5 : IN signed (4 DOWNTO 0);

            a : IN signed (31 DOWNTO 0);
            b : IN signed (31 DOWNTO 0);

            a_out : OUT signed (31 DOWNTO 0);
            b_out : OUT signed (31 DOWNTO 0);

            pc : IN signed (15 DOWNTO 0);
            pc_out : OUT signed (15 DOWNTO 0);

            br_flag_out : OUT STD_LOGIC


        );
    END COMPONENT execute;

    SIGNAL clk : STD_LOGIC;

    SIGNAL opC : INTEGER RANGE 0 TO 63;
    SIGNAL opC_out : INTEGER RANGE 0 TO 63;

    SIGNAL r1, r2, r1_out, r2_out : signed (4 DOWNTO 0);
    SIGNAL imm, imm_out : signed (15 DOWNTO 0);

    SIGNAL long_imm, long_imm_out : signed (25 DOWNTO 0);

    SIGNAL r3, r4, r5: signed (4 DOWNTO 0);

    SIGNAL a, b, a_out, b_out : signed (31 DOWNTO 0);

    SIGNAL pc, pc_out : signed (15 DOWNTO 0);

    SIGNAL br_flag_out : STD_LOGIC;


BEGIN
    executeI : execute PORT MAP(clk, opC, opC_out, r1, r2, imm, r1_out, r2_out, imm_out, long_imm, long_imm_out, r3, r4, r5, a, b, a_out, b_out, pc, pc_out, br_flag_out);
    PROCESS IS
    BEGIN
        FOR j IN 1 TO 1000 LOOP
            clk <= '0';
            WAIT FOR 5 ns;
            clk <= '1';
            WAIT FOR 5 ns;
        END LOOP;
        WAIT;
    END PROCESS;
    a <= to_signed(5, 32);
    b <= to_signed(3, 32);

    PROCESS IS
    BEGIN
        FOR j IN 0 TO 14 LOOP
            opC <= j;
            WAIT FOR 20 ns;
        END LOOP;
        WAIT;
    END PROCESS;

END ARCHITECTURE testbench;

waveform.vcd
$date
  Mon Jan  6 13:51:06 2025
$end
$version
  GHDL v0
$end
$timescale
  1 fs
$end
$scope module standard $end
$upscope $end
$scope module textio $end
$upscope $end
$scope module std_logic_1164 $end
$upscope $end
$scope module numeric_std $end
$upscope $end
$scope module mydefinitions $end
$upscope $end
$scope module executetest $end
$var reg 1 ! clk $end
$var integer 32 " opc $end
$var integer 32 # opc_out $end
$var reg 5 $ r1[4:0] $end
$var reg 5 % r2[4:0] $end
$var reg 5 & r1_out[4:0] $end
$var reg 5 ' r2_out[4:0] $end
$var reg 16 ( imm[15:0] $end
$var reg 16 ) imm_out[15:0] $end
$var reg 26 * long_imm[25:0] $end
$var reg 26 + long_imm_out[25:0] $end
$var reg 5 , r3[4:0] $end
$var reg 5 - r4[4:0] $end
$var reg 5 . r5[4:0] $end
$var reg 32 / a[31:0] $end
$var reg 32 0 b[31:0] $end
$var reg 32 1 a_out[31:0] $end
$var reg 32 2 b_out[31:0] $end
$var reg 16 3 pc[15:0] $end
$var reg 16 4 pc_out[15:0] $end
$var reg 1 5 br_flag_out $end
$scope module executei $end
$var reg 1 6 clk $end
$var integer 32 7 opc $end
$var integer 32 8 opc_out $end
$var reg 5 9 r1[4:0] $end
$var reg 5 : r2[4:0] $end
$var reg 16 ; imm[15:0] $end
$var reg 5 < r1_out[4:0] $end
$var reg 5 = r2_out[4:0] $end
$var reg 16 > imm_out[15:0] $end
$var reg 26 ? long_imm[25:0] $end
$var reg 26 @ long_imm_out[25:0] $end
$var reg 5 A r3[4:0] $end
$var reg 5 B r4[4:0] $end
$var reg 5 C r5[4:0] $end
$var reg 32 D a[31:0] $end
$var reg 32 E b[31:0] $end
$var reg 32 F a_out[31:0] $end
$var reg 32 G b_out[31:0] $end
$var reg 16 H pc[15:0] $end
$var reg 16 I pc_out[15:0] $end
$var reg 1 J br_flag_out $end
$var reg 32 K alu_signal[31:0] $end
$var reg 1 L br_signal $end
$scope module alui $end
$var reg 32 M a[31:0] $end
$var reg 32 N b[31:0] $end
$var reg 16 O imm[15:0] $end
$var integer 32 P opc $end
$var reg 32 Q alu_out[31:0] $end
$var reg 1 R br_flag $end
$var reg 64 S product[63:0] $end
$upscope $end
$upscope $end
$upscope $end
$enddefinitions $end
#0
0!
b0 "
b0 #
bUUUUU $
bUUUUU %
bUUUUU &
bUUUUU '
bUUUUUUUUUUUUUUUU (
bUUUUUUUUUUUUUUUU )
bUUUUUUUUUUUUUUUUUUUUUUUUUU *
bUUUUUUUUUUUUUUUUUUUUUUUUUU +
bUUUUU ,
bUUUUU -
bUUUUU .
b00000000000000000000000000000101 /
b00000000000000000000000000000011 0
bUUUUUUUUUUUUUUUUUUUUUUUUUUUUUUUU 1
bUUUUUUUUUUUUUUUUUUUUUUUUUUUUUUUU 2
bUUUUUUUUUUUUUUUU 3
bUUUUUUUUUUUUUUUU 4
U5
06
b0 7
b0 8
bUUUUU 9
bUUUUU :
bUUUUUUUUUUUUUUUU ;
bUUUUU <
bUUUUU =
bUUUUUUUUUUUUUUUU >
bUUUUUUUUUUUUUUUUUUUUUUUUUU ?
bUUUUUUUUUUUUUUUUUUUUUUUUUU @
bUUUUU A
bUUUUU B
bUUUUU C
b00000000000000000000000000000101 D
b00000000000000000000000000000011 E
bUUUUUUUUUUUUUUUUUUUUUUUUUUUUUUUU F
bUUUUUUUUUUUUUUUUUUUUUUUUUUUUUUUU G
bUUUUUUUUUUUUUUUU H
bUUUUUUUUUUUUUUUU I
UJ
b00000000000000000000000000001000 K
-L
b00000000000000000000000000000101 M
b00000000000000000000000000000011 N
bUUUUUUUUUUUUUUUU O
b0 P
b00000000000000000000000000001000 Q
-R
bUUUUUUUUUUUUUUUUUUUUUUUUUUUUUUUUUUUUUUUUUUUUUUUUUUUUUUUUUUUUUUUU S
#5000000
1!
b00000000000000000000000000000101 1
b00000000000000000000000000001000 2
-5
16
b00000000000000000000000000000101 F
b00000000000000000000000000001000 G
-J
#10000000
0!
06
#15000000
1!
16
#20000000
0!
b1 "
06
b1 7
b00000000000000000000000000000010 K
b1 P
b00000000000000000000000000000010 Q
#25000000
1!
b1 #
b00000000000000000000000000000010 2
16
b1 8
b00000000000000000000000000000010 G
#30000000
0!
06
#35000000
1!
16
#40000000
0!
b10 "
06
b10 7
b11111111111111111111111111111011 K
b10 P
b11111111111111111111111111111011 Q
#45000000
1!
b10 #
b11111111111111111111111111111011 2
16
b10 8
b11111111111111111111111111111011 G
#50000000
0!
06
#55000000
1!
16
#60000000
0!
b11 "
06
b11 7
bUUUUUUUUUUUUUUUUUUUUUUUUUUUUUUUU K
b11 P
bUUUUUUUUUUUUUUUUUUUUUUUUUUUUUUUU Q
b0000000000000000000000000000000000000000000000000000000000001111 S
#65000000
1!
b11 #
bUUUUUUUUUUUUUUUUUUUUUUUUUUUUUUUU 2
16
b11 8
bUUUUUUUUUUUUUUUUUUUUUUUUUUUUUUUU G
#70000000
0!
06
#75000000
1!
16
#80000000
0!
b100 "
06
b100 7
b00000000000000000000000000000001 K
b100 P
b00000000000000000000000000000001 Q
#85000000
1!
b100 #
b00000000000000000000000000000001 2
16
b100 8
b00000000000000000000000000000001 G
#90000000
0!
06
#95000000
1!
16
#100000000
0!
b101 "
06
b101 7
b00000000000000000000000000000010 K
b101 P
b00000000000000000000000000000010 Q
#105000000
1!
b101 #
b00000000000000000000000000000010 2
16
b101 8
b00000000000000000000000000000010 G
#110000000
0!
06
#115000000
1!
16
#120000000
0!
b110 "
06
b110 7
b11111111111111111111111111111010 K
b110 P
b11111111111111111111111111111010 Q
#125000000
1!
b110 #
b11111111111111111111111111111010 2
16
b110 8
b11111111111111111111111111111010 G
#130000000
0!
06
#135000000
1!
16
#140000000
0!
b111 "
06
b111 7
b00000000000000000000000000000001 K
b111 P
b00000000000000000000000000000001 Q
#145000000
1!
b111 #
b00000000000000000000000000000001 2
16
b111 8
b00000000000000000000000000000001 G
#150000000
0!
06
#155000000
1!
16
#160000000
0!
b1000 "
06
b1000 7
b00000000000000000000000000000111 K
b1000 P
b00000000000000000000000000000111 Q
#165000000
1!
b1000 #
b00000000000000000000000000000111 2
16
b1000 8
b00000000000000000000000000000111 G
#170000000
0!
06
#175000000
1!
16
#180000000
0!
b1001 "
06
b1001 7
b-------------------------------- K
0L
b1001 P
b-------------------------------- Q
0R
#185000000
1!
b1001 #
b00000000000000000000000000000011 2
05
16
b1001 8
b00000000000000000000000000000011 G
0J
#190000000
0!
06
#195000000
1!
16
#200000000
0!
b1010 "
06
b1010 7
1L
b1010 P
1R
#205000000
1!
b1010 #
15
16
b1010 8
1J
#210000000
0!
06
#215000000
1!
16
#220000000
0!
b1011 "
06
b1011 7
0L
b1011 P
0R
#225000000
1!
b1011 #
05
16
b1011 8
0J
#230000000
0!
06
#235000000
1!
16
#240000000
0!
b1100 "
06
b1100 7
-L
b1100 P
-R
#245000000
1!
b1100 #
-5
16
b1100 8
-J
#250000000
0!
06
#255000000
1!
16
#260000000
0!
b1101 "
06
b1101 7
b1101 P
#265000000
1!
b1101 #
16
b1101 8
#270000000
0!
06
#275000000
1!
16
#280000000
0!
b1110 "
06
b1110 7
b1110 P
#285000000
1!
b1110 #
16
b1110 8
