execute.vhd
LIBRARY ieee;
USE ieee.std_logic_1164.ALL;
USE ieee.numeric_std.ALL;

USE work.mydefinitions.ALL;

ENTITY alu IS
	PORT (
		a : IN signed (31 DOWNTO 0);
		b : IN signed (31 DOWNTO 0);
		imm : IN signed (15 DOWNTO 0);
		opC : IN INTEGER RANGE 0 TO 63;
		alu_out : OUT signed (31 DOWNTO 0);
		br_flag : OUT STD_LOGIC
	);
END ENTITY alu;

ARCHITECTURE alu_architecture OF alu IS
	SIGNAL product : signed(63 DOWNTO 0);
BEGIN
	PROCESS (a, b, imm, opC) IS
	BEGIN
		alu_out <= (OTHERS => '-');
		br_flag <= '-';
		CASE opC IS
			WHEN add =>
				alu_out <= a + b;
			WHEN subt =>
				alu_out <= a - b;
			WHEN neg =>
				alu_out <= 0 - a;
			WHEN mul =>
				product <= a * b;
				alu_out <= product(31 DOWNTO 0);
			WHEN div =>
				alu_out <= a / b;
			WHEN modu =>
				alu_out <= a MOD b;
			WHEN nicht =>
				alu_out <= NOT a;
			WHEN und =>
				alu_out <= a AND b;
			WHEN oder =>
				alu_out <= a OR b;
			WHEN beq =>
				IF a = b THEN
					br_flag <= '1';
				ELSE
					br_flag <= '0';
				END IF;
			WHEN bneq =>
				IF a = b THEN
					br_flag <= '0';
				ELSE
					br_flag <= '1';
				END IF;
			WHEN blt =>
				IF a < b THEN
					br_flag <= '1';
				ELSE
					br_flag <= '0';
				END IF;
			WHEN OTHERS =>
				NULL;

		END CASE;

	END PROCESS;

END ARCHITECTURE;

LIBRARY ieee;
USE ieee.std_logic_1164.ALL;
USE ieee.numeric_std.ALL;

USE work.mydefinitions.ALL;

ENTITY execute IS
	PORT (
		clk : IN STD_LOGIC;

		opC : IN INTEGER RANGE 0 TO 63;
		opC_out : OUT INTEGER RANGE 0 TO 63;

		r1 : IN signed (4 DOWNTO 0);
		r2 : IN signed (4 DOWNTO 0);
		imm : IN signed (15 DOWNTO 0);
		r1_out : OUT signed (4 DOWNTO 0);
		r2_out : OUT signed (4 DOWNTO 0);
		imm_out : OUT signed (15 DOWNTO 0);

		long_imm : IN signed (25 DOWNTO 0);
		long_imm_out : OUT signed (25 DOWNTO 0);

		r3 : IN signed (4 DOWNTO 0);
		r4 : IN signed (4 DOWNTO 0);
		r5 : IN signed (4 DOWNTO 0);
		r3_out : OUT signed (4 DOWNTO 0);
		r4_out : OUT signed (4 DOWNTO 0);
		r5_out : OUT signed (4 DOWNTO 0);

		a : IN signed (31 DOWNTO 0);
		b : IN signed (31 DOWNTO 0);

		a_out : OUT signed (31 DOWNTO 0);
		b_out : OUT signed (31 DOWNTO 0);

		pc : IN signed (4 DOWNTO 0);
		pc_out : OUT signed (4 DOWNTO 0);

		alu_out : OUT signed (31 DOWNTO 0);
		br_flag_out : OUT STD_LOGIC;

		wb_addr : OUT signed (4 DOWNTO 0)

	);
END ENTITY execute;

ARCHITECTURE execute_architecture OF execute IS

	COMPONENT alu IS
		PORT (
			a : IN signed (31 DOWNTO 0);
			b : IN signed (31 DOWNTO 0);
			imm : IN signed (15 DOWNTO 0);
			opC : IN INTEGER RANGE 0 TO 63;
			alu_out : OUT signed (31 DOWNTO 0);
			br_flag : OUT STD_LOGIC
		);
	END COMPONENT alu;

	SIGNAL alu_signal : signed(31 DOWNTO 0);
	SIGNAL br_signal : STD_LOGIC;
BEGIN

	assign : PROCESS (clk) IS
	BEGIN
		IF rising_edge(clk) THEN
			opC_out <= opC;

			r1_out <= r1;
			r2_out <= r2;
			imm_out <= imm;

			long_imm_out <= long_imm;
			r3_out <= r3;
			r4_out <= r4;
			r5_out <= r5;

			a_out <= a;
			b_out <= b;

			pc_out <= pc;

			alu_out <= alu_signal;
			br_flag_out <= br_signal;

		END IF;
	END PROCESS assign;
	ALUI : alu
	PORT MAP(
		a => a,
		b => b,
		imm => imm,
		opC => opC,
		alu_out => alu_signal,
		br_flag => br_signal
	);

END ARCHITECTURE execute_architecture;

executeTest.vhd
LIBRARY ieee;
USE ieee.std_logic_1164.ALL;
USE ieee.numeric_std.ALL;

ENTITY executeTest IS

END ENTITY executeTest;

ARCHITECTURE testbench OF executeTest IS

    COMPONENT execute IS
        PORT (
            clk : IN STD_LOGIC;

            opC : IN INTEGER RANGE 0 TO 63;
            opC_out : OUT INTEGER RANGE 0 TO 63;

            r1 : IN signed (4 DOWNTO 0);
            r2 : IN signed (4 DOWNTO 0);
            imm : IN signed (15 DOWNTO 0);
            r1_out : OUT signed (4 DOWNTO 0);
            r2_out : OUT signed (4 DOWNTO 0);
            imm_out : OUT signed (15 DOWNTO 0);

            long_imm : IN signed (25 DOWNTO 0);
            long_imm_out : OUT signed (25 DOWNTO 0);

            r3 : IN signed (4 DOWNTO 0);
            r4 : IN signed (4 DOWNTO 0);
            r5 : IN signed (4 DOWNTO 0);
            r3_out : OUT signed (4 DOWNTO 0);
            r4_out : OUT signed (4 DOWNTO 0);
            r5_out : OUT signed (4 DOWNTO 0);

            a : IN signed (31 DOWNTO 0);
            b : IN signed (31 DOWNTO 0);

            a_out : OUT signed (31 DOWNTO 0);
            b_out : OUT signed (31 DOWNTO 0);

            pc : IN signed (4 DOWNTO 0);
            pc_out : OUT signed (4 DOWNTO 0);

            alu_out : OUT signed (31 DOWNTO 0);
            br_flag_out : OUT STD_LOGIC;
            
            wb_addr : OUT signed (4 DOWNTO 0)

        );
    END COMPONENT execute;

    SIGNAL clk : STD_LOGIC;

    SIGNAL opC : INTEGER RANGE 0 TO 63;
    SIGNAL opC_out : INTEGER RANGE 0 TO 63;

    SIGNAL r1, r2, r1_out, r2_out : signed (4 DOWNTO 0);
    SIGNAL imm, imm_out : signed (15 DOWNTO 0);

    SIGNAL long_imm, long_imm_out : signed (25 DOWNTO 0);

    SIGNAL r3, r4, r5, r3_out, r4_out, r5_out : signed (4 DOWNTO 0);

    SIGNAL a, b , a_out, b_out : signed (31 DOWNTO 0);

    SIGNAL pc, pc_out : signed (4 DOWNTO 0);

    SIGNAL alu_out : signed (31 DOWNTO 0);
    SIGNAL br_flag_out : STD_LOGIC;

    SIGNAL wb_addr : signed (4 DOWNTO 0);


BEGIN
    executeI : execute PORT MAP(clk, opC, opC_out, r1, r2, imm, r1_out, r2_out, imm_out, long_imm, long_imm_out, r3, r4, r5, r3_out, r4_out, r5_out, a, b, a_out, b_out, pc, pc_out, alu_out, br_flag_out, wb_addr);
    PROCESS IS
    BEGIN
        FOR j IN 1 TO 1000 LOOP
            clk <= '0';
            WAIT FOR 5 ns;
            clk <= '1';
            WAIT FOR 5 ns;
        END LOOP;
        WAIT;
    END PROCESS;
    a <= to_signed(5, 32);
    b <= to_signed(3, 32);

    PROCESS IS
    BEGIN
        FOR j IN 0 TO 14 LOOP
                opC <= j;
            WAIT FOR 20 ns;
        END LOOP;
        WAIT;
    END PROCESS;

END ARCHITECTURE testbench;

waveform.vcd
$date
  Sat Dec 21 12:44:10 2024
$end
$version
  GHDL v0
$end
$timescale
  1 fs
$end
$scope module standard $end
$upscope $end
$scope module std_logic_1164 $end
$upscope $end
$scope module numeric_std $end
$upscope $end
$scope module mydefinitions $end
$upscope $end
$scope module executetest $end
$var reg 1 ! clk $end
$var integer 32 " opc $end
$var integer 32 # opc_out $end
$var reg 5 $ r1[4:0] $end
$var reg 5 % r2[4:0] $end
$var reg 5 & r1_out[4:0] $end
$var reg 5 ' r2_out[4:0] $end
$var reg 16 ( imm[15:0] $end
$var reg 16 ) imm_out[15:0] $end
$var reg 26 * long_imm[25:0] $end
$var reg 26 + long_imm_out[25:0] $end
$var reg 5 , r3[4:0] $end
$var reg 5 - r4[4:0] $end
$var reg 5 . r5[4:0] $end
$var reg 5 / r3_out[4:0] $end
$var reg 5 0 r4_out[4:0] $end
$var reg 5 1 r5_out[4:0] $end
$var reg 32 2 a[31:0] $end
$var reg 32 3 b[31:0] $end
$var reg 32 4 a_out[31:0] $end
$var reg 32 5 b_out[31:0] $end
$var reg 5 6 pc[4:0] $end
$var reg 5 7 pc_out[4:0] $end
$var reg 32 8 alu_out[31:0] $end
$var reg 1 9 br_flag_out $end
$var reg 5 : wb_addr[4:0] $end
$scope module executei $end
$var reg 1 ; clk $end
$var integer 32 < opc $end
$var integer 32 = opc_out $end
$var reg 5 > r1[4:0] $end
$var reg 5 ? r2[4:0] $end
$var reg 16 @ imm[15:0] $end
$var reg 5 A r1_out[4:0] $end
$var reg 5 B r2_out[4:0] $end
$var reg 16 C imm_out[15:0] $end
$var reg 26 D long_imm[25:0] $end
$var reg 26 E long_imm_out[25:0] $end
$var reg 5 F r3[4:0] $end
$var reg 5 G r4[4:0] $end
$var reg 5 H r5[4:0] $end
$var reg 5 I r3_out[4:0] $end
$var reg 5 J r4_out[4:0] $end
$var reg 5 K r5_out[4:0] $end
$var reg 32 L a[31:0] $end
$var reg 32 M b[31:0] $end
$var reg 32 N a_out[31:0] $end
$var reg 32 O b_out[31:0] $end
$var reg 5 P pc[4:0] $end
$var reg 5 Q pc_out[4:0] $end
$var reg 32 R alu_out[31:0] $end
$var reg 1 S br_flag_out $end
$var reg 5 T wb_addr[4:0] $end
$var reg 32 U alu_signal[31:0] $end
$var reg 1 V br_signal $end
$scope module alui $end
$var reg 32 W a[31:0] $end
$var reg 32 X b[31:0] $end
$var reg 16 Y imm[15:0] $end
$var integer 32 Z opc $end
$var reg 32 [ alu_out[31:0] $end
$var reg 1 \ br_flag $end
$var reg 64 ] product[63:0] $end
$upscope $end
$upscope $end
$upscope $end
$enddefinitions $end
#0
0!
b0 "
b0 #
bUUUUU $
bUUUUU %
bUUUUU &
bUUUUU '
bUUUUUUUUUUUUUUUU (
bUUUUUUUUUUUUUUUU )
bUUUUUUUUUUUUUUUUUUUUUUUUUU *
bUUUUUUUUUUUUUUUUUUUUUUUUUU +
bUUUUU ,
bUUUUU -
bUUUUU .
bUUUUU /
bUUUUU 0
bUUUUU 1
b00000000000000000000000000000101 2
b00000000000000000000000000000011 3
bUUUUUUUUUUUUUUUUUUUUUUUUUUUUUUUU 4
bUUUUUUUUUUUUUUUUUUUUUUUUUUUUUUUU 5
bUUUUU 6
bUUUUU 7
bUUUUUUUUUUUUUUUUUUUUUUUUUUUUUUUU 8
U9
bUUUUU :
0;
b0 <
b0 =
bUUUUU >
bUUUUU ?
bUUUUUUUUUUUUUUUU @
bUUUUU A
bUUUUU B
bUUUUUUUUUUUUUUUU C
bUUUUUUUUUUUUUUUUUUUUUUUUUU D
bUUUUUUUUUUUUUUUUUUUUUUUUUU E
bUUUUU F
bUUUUU G
bUUUUU H
bUUUUU I
bUUUUU J
bUUUUU K
b00000000000000000000000000000101 L
b00000000000000000000000000000011 M
bUUUUUUUUUUUUUUUUUUUUUUUUUUUUUUUU N
bUUUUUUUUUUUUUUUUUUUUUUUUUUUUUUUU O
bUUUUU P
bUUUUU Q
bUUUUUUUUUUUUUUUUUUUUUUUUUUUUUUUU R
US
bUUUUU T
b00000000000000000000000000001000 U
-V
b00000000000000000000000000000101 W
b00000000000000000000000000000011 X
bUUUUUUUUUUUUUUUU Y
b0 Z
b00000000000000000000000000001000 [
-\
bUUUUUUUUUUUUUUUUUUUUUUUUUUUUUUUUUUUUUUUUUUUUUUUUUUUUUUUUUUUUUUUU ]
#5000000
1!
b00000000000000000000000000000101 4
b00000000000000000000000000000011 5
b00000000000000000000000000001000 8
-9
1;
b00000000000000000000000000000101 N
b00000000000000000000000000000011 O
b00000000000000000000000000001000 R
-S
#10000000
0!
0;
#15000000
1!
1;
#20000000
0!
b1 "
0;
b1 <
b00000000000000000000000000000010 U
b1 Z
b00000000000000000000000000000010 [
#25000000
1!
b1 #
b00000000000000000000000000000010 8
1;
b1 =
b00000000000000000000000000000010 R
#30000000
0!
0;
#35000000
1!
1;
#40000000
0!
b10 "
0;
b10 <
b11111111111111111111111111111011 U
b10 Z
b11111111111111111111111111111011 [
#45000000
1!
b10 #
b11111111111111111111111111111011 8
1;
b10 =
b11111111111111111111111111111011 R
#50000000
0!
0;
#55000000
1!
1;
#60000000
0!
b11 "
0;
b11 <
bUUUUUUUUUUUUUUUUUUUUUUUUUUUUUUUU U
b11 Z
bUUUUUUUUUUUUUUUUUUUUUUUUUUUUUUUU [
b0000000000000000000000000000000000000000000000000000000000001111 ]
#65000000
1!
b11 #
bUUUUUUUUUUUUUUUUUUUUUUUUUUUUUUUU 8
1;
b11 =
bUUUUUUUUUUUUUUUUUUUUUUUUUUUUUUUU R
#70000000
0!
0;
#75000000
1!
1;
#80000000
0!
b100 "
0;
b100 <
b00000000000000000000000000000001 U
b100 Z
b00000000000000000000000000000001 [
#85000000
1!
b100 #
b00000000000000000000000000000001 8
1;
b100 =
b00000000000000000000000000000001 R
#90000000
0!
0;
#95000000
1!
1;
#100000000
0!
b101 "
0;
b101 <
b00000000000000000000000000000010 U
b101 Z
b00000000000000000000000000000010 [
#105000000
1!
b101 #
b00000000000000000000000000000010 8
1;
b101 =
b00000000000000000000000000000010 R
#110000000
0!
0;
#115000000
1!
1;
#120000000
0!
b110 "
0;
b110 <
b11111111111111111111111111111010 U
b110 Z
b11111111111111111111111111111010 [
#125000000
1!
b110 #
b11111111111111111111111111111010 8
1;
b110 =
b11111111111111111111111111111010 R
#130000000
0!
0;
#135000000
1!
1;
#140000000
0!
b111 "
0;
b111 <
b00000000000000000000000000000001 U
b111 Z
b00000000000000000000000000000001 [
#145000000
1!
b111 #
b00000000000000000000000000000001 8
1;
b111 =
b00000000000000000000000000000001 R
#150000000
0!
0;
#155000000
1!
1;
#160000000
0!
b1000 "
0;
b1000 <
b00000000000000000000000000000111 U
b1000 Z
b00000000000000000000000000000111 [
#165000000
1!
b1000 #
b00000000000000000000000000000111 8
1;
b1000 =
b00000000000000000000000000000111 R
#170000000
0!
0;
#175000000
1!
1;
#180000000
0!
b1001 "
0;
b1001 <
b-------------------------------- U
0V
b1001 Z
b-------------------------------- [
0\
#185000000
1!
b1001 #
b-------------------------------- 8
09
1;
b1001 =
b-------------------------------- R
0S
#190000000
0!
0;
#195000000
1!
1;
#200000000
0!
b1010 "
0;
b1010 <
1V
b1010 Z
1\
#205000000
1!
b1010 #
19
1;
b1010 =
1S
#210000000
0!
0;
#215000000
1!
1;
#220000000
0!
b1011 "
0;
b1011 <
0V
b1011 Z
0\
#225000000
1!
b1011 #
09
1;
b1011 =
0S
#230000000
0!
0;
#235000000
1!
1;
#240000000
0!
b1100 "
0;
b1100 <
-V
b1100 Z
-\
#245000000
1!
b1100 #
-9
1;
b1100 =
-S
#250000000
0!
0;
#255000000
1!
1;
#260000000
0!
b1101 "
0;
b1101 <
b1101 Z
#265000000
1!
b1101 #
1;
b1101 =
#270000000
0!
0;
#275000000
1!
1;
#280000000
0!
b1110 "
0;
b1110 <
b1110 Z
#285000000
1!
b1110 #
1;
b1110 =
